web3_common/__init__.py
web3_common/rpc.py
web3_common/util.py
web3_common-1.0.2.dist-info/METADATA
web3_common-1.0.2.dist-info/WHEEL
web3_common-1.0.2.dist-info/top_level.txt
web3_common-1.0.2.dist-info/RECORD
